m17/__init__.py
m17/__main__.py
m17/address.py
m17/apps.py
m17/audio_test.py
m17/blocks.py
m17/client.py
m17/const.py
m17/framer.py
m17/frames.py
m17/misc.py
m17/network.py
m17/sanity_check.py
m17/voipsim.py
m17-0.1.0.dist-info/METADATA
m17-0.1.0.dist-info/WHEEL
m17-0.1.0.dist-info/RECORD
