Metadata-Version: 2.4
Name: m17
Version: 0.1.0
Summary: 
Author: Luke Stamm
Author-email: we3dz@we3dz.com
Requires-Python: >=3.12,<4.0
Classifier: Programming Language :: Python :: 3
Classifier: Programming Language :: Python :: 3.12
Classifier: Programming Language :: Python :: 3.13
Classifier: Programming Language :: Python :: 3.14
Requires-Dist: bitstruct (>=8.19.0,<9.0.0)
Requires-Dist: certifi (>=2024.12.14,<2025.0.0)
Requires-Dist: cffi (>=1.17.1,<2.0.0)
Requires-Dist: chardet (>=5.2.0,<6.0.0)
Requires-Dist: cython (>=3.0.11,<4.0.0)
Requires-Dist: idna (>=3.10,<4.0)
Requires-Dist: kademlia (>=2.2.2,<3.0.0)
Requires-Dist: numpy (>=2.2.1,<3.0.0)
Requires-Dist: pycodec2 (>=4.0.1,<5.0.0)
Requires-Dist: pycparser (>=2.22,<3.0)
Requires-Dist: pydantic (>=2.9.2,<3.0.0)
Requires-Dist: pydantic-core (>=2.23.4,<3.0.0)
Requires-Dist: pydantic-settings (>=2.5.2,<3.0.0)
Requires-Dist: requests (>=2.32.3,<3.0.0)
Requires-Dist: rpcudp (>=5.0.0,<6.0.0)
Requires-Dist: samplerate (>=0.2.1,<0.3.0)
Requires-Dist: soundcard (>=0.4.3,<0.5.0)
Requires-Dist: u-msgpack-python (>=2.8.0,<3.0.0)
Requires-Dist: urllib3 (>=2.3.0,<3.0.0)
